grimp_package_metrics/__init__.py
grimp_package_metrics/coupling_metrics.py
grimp_package_metrics/dependency_cycles.py
grimp_package_metrics-0.1.0.dist-info/METADATA
grimp_package_metrics-0.1.0.dist-info/WHEEL
grimp_package_metrics-0.1.0.dist-info/namespace_packages.txt
grimp_package_metrics-0.1.0.dist-info/top_level.txt
grimp_package_metrics-0.1.0.dist-info/RECORD
