Metadata-Version: 2.1
Name: grimp-package-metrics
Version: 0.1.0
Summary: An example distribution built with Pants.
Home-page: UNKNOWN
Author: Pantsbuild
License: UNKNOWN
Platform: UNKNOWN
Classifier: Programming Language :: Python :: 3.7
Requires-Dist: grimp (<2.0.0,>=1.2.3)
Requires-Dist: networkx (<3.0.0,>=2.1.0)
